flask_rest4/__init__.py
flask_rest4/api.py
flask_rest4/decorators.py
flask_rest4/errors.py
flask_rest4/response.py
flask_rest4/settings.py
flask_rest4-0.3.0.dist-info/DESCRIPTION.rst
flask_rest4-0.3.0.dist-info/METADATA
flask_rest4-0.3.0.dist-info/RECORD
flask_rest4-0.3.0.dist-info/WHEEL
flask_rest4-0.3.0.dist-info/metadata.json
flask_rest4-0.3.0.dist-info/top_level.txt
