Metadata-Version: 2.0
Name: flask-rest4
Version: 0.3.0
Summary: Elegant RESTful API for your Flask apps.
Home-page: https://github.com/squirrelmajik/flask_rest4
Author: majik
Author-email: me@yamajik.com
License: See License
Platform: any
Classifier: Environment :: Web Environment
Classifier: Intended Audience :: Developers
Classifier: License :: OSI Approved :: BSD License
Classifier: Operating System :: OS Independent
Classifier: Programming Language :: Python
Classifier: Topic :: Internet :: WWW/HTTP :: Dynamic Content
Classifier: Topic :: Software Development :: Libraries :: Python Modules
Requires-Dist: Flask
